ace/__init__.py
ace/middleware.py
ace/playbook.py
ace/prompts.py
ace/py.typed
ace/types.py
ace/utils.py
langchain_continuous_learning-0.1.0.dist-info/METADATA
langchain_continuous_learning-0.1.0.dist-info/WHEEL
langchain_continuous_learning-0.1.0.dist-info/RECORD
