Metadata-Version: 2.4
Name: langchain-continuous-learning
Version: 0.1.0
Summary: Agentic Context Engineering (ACE) middleware for LangChain v1 agents
Project-URL: Homepage, https://github.com/dkondo/langchain-continuous-learning
Project-URL: Documentation, https://github.com/dkondo/langchain-continuous-learning#readme
Project-URL: Repository, https://github.com/dkondo/langchain-continuous-learning
Project-URL: Source Code, https://github.com/dkondo/langchain-continuous-learning/tree/main/libs/langchain-continuous-learning
Author-email: Derrick Kondo <dkondo@gmail.com>
License: MIT
Classifier: Development Status :: 4 - Beta
Classifier: Intended Audience :: Developers
Classifier: License :: OSI Approved :: MIT License
Classifier: Operating System :: OS Independent
Classifier: Programming Language :: Python :: 3
Classifier: Programming Language :: Python :: 3.10
Classifier: Programming Language :: Python :: 3.11
Classifier: Programming Language :: Python :: 3.12
Classifier: Topic :: Scientific/Engineering :: Artificial Intelligence
Requires-Python: <4.0,>=3.10
Requires-Dist: langchain-core<1.0.0,>=0.3.0
Requires-Dist: langgraph<1.0.0,>=0.2.0
Requires-Dist: pydantic<3.0.0,>=2.7.4
